haptik_code_library/__init__.py
haptik_code_library/haptik_requests/__init__.py
haptik_code_library/haptik_requests/const.py
haptik_code_library-0.3.dist-info/METADATA
haptik_code_library-0.3.dist-info/WHEEL
haptik_code_library-0.3.dist-info/top_level.txt
haptik_code_library-0.3.dist-info/RECORD
